CHANGELOG.md
README.md
pytempl_cli/__init__.py
pytempl_cli/__main__.py
pytempl_cli/build_process.py
pytempl_cli/cli.py
pytempl_cli/loader.py
pytempl_cli/utils.py
pytempl_cli-0.0.1a2.dist-info/LICENCE.md
pytempl_cli-0.0.1a2.dist-info/METADATA
pytempl_cli-0.0.1a2.dist-info/WHEEL
pytempl_cli-0.0.1a2.dist-info/entry_points.txt
pytempl_cli-0.0.1a2.dist-info/RECORD
